streamlit_antd_components/__init__.py
streamlit_antd_components/frontend/build/asset-manifest.json
streamlit_antd_components/frontend/build/bootstrap.min.css
streamlit_antd_components/frontend/build/index.html
streamlit_antd_components/frontend/build/static/css/2.abca270b.chunk.css
streamlit_antd_components/frontend/build/static/css/2.abca270b.chunk.css.map
streamlit_antd_components/frontend/build/static/css/main.c4a82649.chunk.css
streamlit_antd_components/frontend/build/static/css/main.c4a82649.chunk.css.map
streamlit_antd_components/frontend/build/static/js/2.2c85eb9b.chunk.js
streamlit_antd_components/frontend/build/static/js/2.2c85eb9b.chunk.js.LICENSE.txt
streamlit_antd_components/frontend/build/static/js/2.2c85eb9b.chunk.js.map
streamlit_antd_components/frontend/build/static/js/main.b514de94.chunk.js
streamlit_antd_components/frontend/build/static/js/main.b514de94.chunk.js.map
streamlit_antd_components/frontend/build/static/js/runtime-main.6b397ac4.js
streamlit_antd_components/frontend/build/static/js/runtime-main.6b397ac4.js.map
streamlit_antd_components/frontend/build/static/media/bootstrap-icons.449ad8ad.woff
streamlit_antd_components/frontend/build/static/media/bootstrap-icons.dea24bf5.woff2
streamlit_antd_components/utils/__init__.py
streamlit_antd_components/utils/callback.py
streamlit_antd_components/utils/component_func.py
streamlit_antd_components/utils/data_class.py
streamlit_antd_components/utils/parser.py
streamlit_antd_components/utils/setting.py
streamlit_antd_components/widgets/__init__.py
streamlit_antd_components/widgets/alert.py
streamlit_antd_components/widgets/buttons.py
streamlit_antd_components/widgets/cascader.py
streamlit_antd_components/widgets/checkbox.py
streamlit_antd_components/widgets/chip.py
streamlit_antd_components/widgets/divider.py
streamlit_antd_components/widgets/menu.py
streamlit_antd_components/widgets/pagination.py
streamlit_antd_components/widgets/rate.py
streamlit_antd_components/widgets/result.py
streamlit_antd_components-0.3.1.dist-info/LICENSE
streamlit_antd_components-0.3.1.dist-info/METADATA
streamlit_antd_components-0.3.1.dist-info/WHEEL
streamlit_antd_components-0.3.1.dist-info/top_level.txt
streamlit_antd_components-0.3.1.dist-info/RECORD
