Metadata-Version: 2.1
Name: streamlit-antd-components
Version: 0.3.1
Summary: streamlit customer components of Antd Design and Mantine
Home-page: https://github.com/nicedouble/StreamlitAntdComponents
Author: jihaoran
License: UNKNOWN
Platform: UNKNOWN
Requires-Python: >=3.8
Requires-Dist: streamlit (>=1.12.0)
